osmose_presets/OsmosePresets.json
osmose_presets/__init__.py
osmose_presets/aligned_data_table.py
osmose_presets/app.py
osmose_presets/config.json
osmose_presets/filter_selector.py
osmose_presets/filters.py
osmose_presets/header_panel.py
osmose_presets/helper_functions.py
osmose_presets/messages.py
osmose_presets/midi_controller.py
osmose_presets/osmose_presets.egg-info/PKG-INFO
osmose_presets/osmose_presets.egg-info/SOURCES.txt
osmose_presets/osmose_presets.egg-info/dependency_links.txt
osmose_presets/osmose_presets.egg-info/entry_points.txt
osmose_presets/osmose_presets.egg-info/requires.txt
osmose_presets/osmose_presets.egg-info/top_level.txt
osmose_presets/osmose_presets.tcss
osmose_presets/preset_data.py
osmose_presets/preset_grid.py
osmose_presets/search_test.py
osmose_presets/test_midiout2.py
osmose_presets/test_preset_change.py
osmose_presets-0.4.0.dist-info/WHEEL
osmose_presets-0.4.0.dist-info/entry_points.txt
osmose_presets-0.4.0.dist-info/METADATA
osmose_presets-0.4.0.dist-info/RECORD
