Metadata-Version: 2.3
Name: osmose-presets
Version: 0.4.0
Summary: Preset Browser for the Expressive E Osmose
Author: Carl Caulkett
Author-email: Carl Caulkett <carl.caulkett@gmail.com>
License:                     GNU GENERAL PUBLIC LICENSE
Requires-Dist: mido>=1.3.3
Requires-Dist: python-rtmidi>=1.5.8
Requires-Dist: textual[syntax]>=6.1.0
Requires-Python: >=3.12
